LICENSE
README.md
setup.cfg
setup.py
vfu/__init__.py
vfu.egg-info/PKG-INFO
vfu.egg-info/SOURCES.txt
vfu.egg-info/dependency_links.txt
vfu.egg-info/top_level.txt